{
  "hash": "04e080e2",
  "configHash": "d09dc820",
  "lockfileHash": "af3d04bc",
  "browserHash": "a599f96a",
  "optimized": {
    "react-dom/client": {
      "src": "../../node_modules/react-dom/client.js",
      "file": "react-dom_client.js",
      "fileHash": "b5ff7d62",
      "needsInterop": true
    },
    "react-router-dom": {
      "src": "../../node_modules/react-router-dom/dist/index.js",
      "file": "react-router-dom.js",
      "fileHash": "de63b2d0",
      "needsInterop": false
    },
    "react-hot-toast": {
      "src": "../../node_modules/react-hot-toast/dist/index.mjs",
      "file": "react-hot-toast.js",
      "fileHash": "73d3cbb6",
      "needsInterop": false
    },
    "react": {
      "src": "../../node_modules/react/index.js",
      "file": "react.js",
      "fileHash": "d4d42bca",
      "needsInterop": true
    },
    "secretjs": {
      "src": "../../node_modules/secretjs/dist/browser.js",
      "file": "secretjs.js",
      "fileHash": "702a9374",
      "needsInterop": true
    },
    "ethers": {
      "src": "../../node_modules/ethers/lib.esm/index.js",
      "file": "ethers.js",
      "fileHash": "c63ae952",
      "needsInterop": false
    },
    "styled-components": {
      "src": "../../node_modules/styled-components/dist/styled-components.browser.esm.js",
      "file": "styled-components.js",
      "fileHash": "5ffeece6",
      "needsInterop": false
    },
    "@fortawesome/react-fontawesome": {
      "src": "../../node_modules/@fortawesome/react-fontawesome/index.es.js",
      "file": "@fortawesome_react-fontawesome.js",
      "fileHash": "be04a22d",
      "needsInterop": false
    },
    "@fortawesome/free-solid-svg-icons": {
      "src": "../../node_modules/@fortawesome/free-solid-svg-icons/index.mjs",
      "file": "@fortawesome_free-solid-svg-icons.js",
      "fileHash": "275cf7ad",
      "needsInterop": false
    },
    "axios": {
      "src": "../../node_modules/axios/index.js",
      "file": "axios.js",
      "fileHash": "d7e23c0f",
      "needsInterop": false
    },
    "web3": {
      "src": "../../node_modules/web3/lib/esm/index.js",
      "file": "web3.js",
      "fileHash": "fb1be814",
      "needsInterop": false
    },
    "clsx": {
      "src": "../../node_modules/clsx/dist/clsx.mjs",
      "file": "clsx.js",
      "fileHash": "9db2e557",
      "needsInterop": false
    },
    "bignumber.js": {
      "src": "../../node_modules/bignumber.js/bignumber.mjs",
      "file": "bignumber__js.js",
      "fileHash": "74c20fa2",
      "needsInterop": false
    }
  },
  "chunks": {
    "chunk-UFQ7NRIS": {
      "file": "chunk-UFQ7NRIS.js"
    },
    "chunk-YHMG5RUC": {
      "file": "chunk-YHMG5RUC.js"
    },
    "chunk-D7BMRXZE": {
      "file": "chunk-D7BMRXZE.js"
    },
    "chunk-TXPGJST7": {
      "file": "chunk-TXPGJST7.js"
    }
  }
}